nonebot_plugin_jimeng/__init__.py
nonebot_plugin_jimeng/concurrency.py
nonebot_plugin_jimeng/config.py
nonebot_plugin_jimeng/models.py
nonebot_plugin_jimeng/proxy.py
nonebot_plugin_jimeng/session_manager.py
nonebot_plugin_jimeng/utils.py
nonebot_plugin_jimeng-0.4.5.dist-info/WHEEL
nonebot_plugin_jimeng-0.4.5.dist-info/METADATA
nonebot_plugin_jimeng-0.4.5.dist-info/RECORD
