Metadata-Version: 2.3
Name: nonebot-plugin-jimeng
Version: 0.4.5
Summary: 一个基于 NoneBot2 的 AI 绘画插件，通过调用**即梦（Jimeng）**的 OpenAPI 实现文生图和图生图功能。
Author: FlanChanXwO
Author-email: FlanChanXwO <badapple495@outlook.com>
Requires-Dist: aiofiles>=25.1.0
Requires-Dist: httpx>=0.27.0,<1.0.0
Requires-Dist: nonebot-plugin-apscheduler>=0.5.0,<1.0.0
Requires-Dist: nonebot-plugin-localstore>=0.7.4,<1.0.0
Requires-Dist: nonebot2>=2.4.3,<3.0.0
Requires-Dist: nonebot-adapter-onebot>=2.4.6
Requires-Python: >=3.10
Project-URL: Homepage, https://github.com/FlanChanXwO/nonebot-plugin-jimeng
Project-URL: Issues, https://github.com/FlanChanXwO/nonebot-plugin-jimeng/issues
Project-URL: Repository, https://github.com/FlanChanXwO/nonebot-plugin-jimeng.git
